rowland/__init__.py
rowland/client.py
rowland/exceptions.py
rowland/models.py
rowland-0.0.1.dist-info/METADATA
rowland-0.0.1.dist-info/WHEEL
rowland-0.0.1.dist-info/RECORD
