Metadata-Version: 2.4
Name: rowland
Version: 0.0.1
Summary: Python SDK for the Rowland Documents API
Project-URL: Homepage, https://rowland.ai
Author-email: Nolan Tremelling <nolan@rowland.com>
License-Expression: MIT
Requires-Python: >=3.8
Requires-Dist: httpx>=0.24.0
Requires-Dist: pydantic>=2.0.0
